{
  "pages": {
    "home": "Home",
    "about": "Chi sono",
    "frame": "Riferimento 3D"
  },
  "home": {
    "meta": {
      "title": "dirty-geometry — L'uomo dei motivi",
      "description": "Portfolio di dirty-geometry, un designer di motivi con sede in Svizzera."
    },
    "hero": {
      "eyebrow": "Designer di motivi",
      "heading": "dirty-geometry",
      "tagline": "A pasticciare",
      "cta": "Vedi i lavori"
    },
    "problems": {
      "entries": "Voci selezionate",
      "item1": {
        "title": "Motivi tessili",
        "desc": "Strutture intrecciate per moda e interni."
      },
      "item2": {
        "title": "Design di superficie",
        "desc": "Motivi ripetitivi audaci per stampa e media digitali."
      },
      "item3": {
        "title": "Motivi di brand",
        "desc": "Motivi distintivi che definiscono i sistemi di identità."
      }
    },
    "contact": {
      "heading": "Creiamo qualcosa insieme.",
      "cta": "Contattami"
    }
  },
  "about": {
    "meta": {
      "description": "Chi è dirty-geometry, designer di motivi con sede in Svizzera."
    },
    "heading": "Chi è dirty-geometry",
    "subheading": "Con sede in Svizzera, creo motivi che uniscono tradizione e design contemporaneo. Trovami su <a href=\"https://jonasward.ch/dirty-geometry\" target=\"_blank\">jonasward.ch/dirty-geometry</a>."
  },
  "notFound": {
    "meta": {
      "title": "Pagina non trovata — dirty-geometry",
      "description": "Questa pagina non esiste o è stata spostata."
    },
    "eyebrow": "404",
    "heading": "Pagina non trovata",
    "body": "L'indirizzo potrebbe essere errato, oppure la pagina è stata rimossa.",
    "backHome": "Torna alla home",
    "otherLocales": "Home in un'altra lingua"
  }
}
